diffjson/__init__.py
diffjson/branch.py
diffjson/diff.py
diffjson/exceptions_branch.py
diffjson/exceptions_diff.py
diffjson/pcounter.py
diffjson/searchpath/__init__.py
diffjson/searchpath/exceptions.py
diffjson/searchpath/lex.py
diffjson/searchpath/parse.py
diffjson/searchpath/pathtypes.py
diffjson-0.1.2.dist-info/LICENSE
diffjson-0.1.2.dist-info/METADATA
diffjson-0.1.2.dist-info/WHEEL
diffjson-0.1.2.dist-info/top_level.txt
diffjson-0.1.2.dist-info/RECORD
