Metadata-Version: 2.1
Name: diffjson
Version: 0.1.2
Summary: Tools to diff json format data.
Home-page: https://github.com/nfwprod/diffjson
Author: nfwprod@gmail.com
License: MIT
Platform: UNKNOWN
Classifier: Development Status :: 3 - Alpha
Classifier: Intended Audience :: Developers
Classifier: License :: OSI Approved :: MIT License
Classifier: Operating System :: OS Independent
Requires-Dist: ply (>=3.11)
